pypse/__init__.py
pypse/__main__.py
pypse/blocks.py
pypse/compiler.py
pypse/converters.py
pypse/debug.py
pypse/expressions.py
pypse/keys.py
pypse/operators.py
pypse/output.py
pypse/parser.py
pypse/pypse_run.py
pypse/shell.py
pypse/symbols.py
pypse/values.py
pypse-0.0.1.dist-info/LICENCE
pypse-0.0.1.dist-info/METADATA
pypse-0.0.1.dist-info/WHEEL
pypse-0.0.1.dist-info/top_level.txt
pypse-0.0.1.dist-info/RECORD
