Metadata-Version: 2.1
Name: pypse
Version: 0.0.1
Summary: A compiler for Pseudocode written in python
Home-page: https://github.com/HankelBao/PyPse
Author: Hankel Bao
Author-email: hankel.bao@gmail.com
License: UNKNOWN
Platform: UNKNOWN
Classifier: Programming Language :: Python :: 3
Classifier: License :: OSI Approved :: MIT License
Classifier: Operating System :: OS Independent
Requires-Dist: lark-parser
